{
  "buttons.add_column": "Додати стовпець",
  "buttons.add_content": "Додати вміст",
  "buttons.add_display_condition": "Додати умову відображення",
  "buttons.add_field": "Додати поле",
  "buttons.add_new_field": "Додати нове поле",
  "buttons.add_new_item": "Додати новий елемент",
  "buttons.add_row": "Додати рядок",
  "buttons.add_text": "Додати текст",
  "buttons.apply": "Застосувати",
  "buttons.apply_effects": "Застосувати ефекти тощо",
  "buttons.back": "Назад",
  "buttons.background": "Фон",
  "buttons.cancel": "Скасувати",
  "buttons.change": "Змінити",
  "buttons.change_image": "Змінити зображення",
  "buttons.close": "Закрити",
  "buttons.comment": "Коментувати",
  "buttons.corners": "Кути",
  "buttons.crop": "Обітнути",
  "buttons.delete": "Видалити",
  "buttons.deselect": "Скасувати вибір",
  "buttons.desktop": "Робочий стіл",
  "buttons.done": "Готово",
  "buttons.draw": "Малювати",
  "buttons.drawing": "Малюнок",
  "buttons.duplicate": "Дублювати",
  "buttons.duplication_disabled_usage_limit": "Ви не можете дублювати це через обмеження використання",
  "buttons.edit": "Редагувати",
  "buttons.filter": "Фільтрувати",
  "buttons.frame": "Рамка",
  "buttons.history": "Журнал",
  "buttons.merge": "Об’єднати",
  "buttons.mobile": "Мобільний",
  "buttons.more_options": "Більше параметрів",
  "buttons.open": "Відкрити",
  "buttons.remove_column": "Видалити стовпець",
  "buttons.reset": "Скинути",
  "buttons.reset_value": "Перевстановити значення",
  "buttons.resize": "Змінити розмір",
  "buttons.save": "Зберегти",
  "buttons.select": "Вибрати",
  "buttons.shape": "Фігура",
  "buttons.shapes": "Фігури",
  "buttons.show_fewer_options": "Показати менше параметрів",
  "buttons.show_more_options": "Показати більше параметрів",
  "buttons.sticker": "Наклейка",
  "buttons.stickers": "Наклейки",
  "buttons.tablet": "Планшет",
  "buttons.transform": "Перетворити",
  "buttons.update_field": "Оновити поле",
  "buttons.upload": "Завантажити",
  "buttons.upload_image": "Завантажити зображення",
  "buttons.zoom": "Масштабування",
  "collaboration.add_comment": "Додати коментар",
  "collaboration.empty.subtitle": "Ваші теми тут",
  "collaboration.empty.title": "Працювати у команді тепер легко!",
  "collaboration.empty_filtered.subtitle": "відповідає вашим фільтрам",
  "collaboration.empty_filtered.title": "Не знайдена жодна тема",
  "collaboration.exit_mode": "Закрити коментарі",
  "collaboration.filters.all": "Усі",
  "collaboration.filters.only_yours": "Лише ваші",
  "collaboration.filters.resolved": "Вирішено",
  "collaboration.follow_docs_to_setup": "Слідуйте документації, щоб налаштувати командну роботу",
  "collaboration.leave_repply": "Залишити відповідь",
  "collaboration.login_to_collaborate": "Вам потрібно увійти, щоб мати змогу працювати спільно",
  "collaboration.panel.threads": "Теми",
  "collaboration.replies.one": "1 відповідь",
  "collaboration.replies.n": "{n} відповідей",
  "collaboration.replies.none": "Відповідей немає",
  "collaboration.resolve": "Вирішити",
  "collaboration.resolved": "Вирішено",
  "collaboration.types.feedback": "Відгук",
  "collaboration.types.idea": "Ідея",
  "collaboration.types.question": "Питання",
  "collaboration.types.urgent": "Терміново",
  "colors.black": "Чорний",
  "colors.ruby": "Рубін",
  "colors.white": "Білий",
  "content_tools.button": "Кнопка",
  "content_tools.columns": "Стовпці",
  "content_tools.divider": "Розділювач",
  "content_tools.form": "Форма",
  "content_tools.heading": "Заголовок",
  "content_tools.html": "HTML",
  "content_tools.image": "Зображення",
  "content_tools.menu": "Меню",
  "content_tools.social": "Соціальний",
  "content_tools.text": "Текст",
  "content_tools.timer": "Таймер",
  "content_tools.video": "Відео",
  "editor.action_type.label": "Тип дії",
  "editor.align.label": "Вирівняти",
  "editor.alignment.label": "Вирівнювання",
  "editor.all_sides.label": "Усі сторони",
  "editor.alternate_text.label": "Альтернативний текст",
  "editor.anchor.section_already_exists": "Розділ сторінки з такою назвою вже існує",
  "editor.background_color.label": "Колір фону",
  "editor.background_image.center": "Центр",
  "editor.background_image.cover_mode": "Режим обкладинки",
  "editor.background_image.full_width": "Повна ширина",
  "editor.background_image.label": "Зображення фону",
  "editor.background_image.repeat": "Повторити",
  "editor.border.dashed": "Штрихи",
  "editor.border.dotted": "Крапки",
  "editor.border.label": "Межа",
  "editor.border.solid": "Суцільно",
  "editor.bottom.label": "Нижня частина",
  "editor.bottom_left.label": "Знизу зліва",
  "editor.bottom_right.label": "Знизу справа",
  "editor.button_link.label": "Посилання кнопки",
  "editor.color.label": "Колір",
  "editor.colors.label": "Кольори",
  "editor.columns_background.label": "Фон стовпців",
  "editor.container_padding.label": "Заповнення контейнера",
  "editor.content_alignment.label": "Вирівнювання вмісту",
  "editor.content_background_color.label": "Колір фону вмісту",
  "editor.content_width.label": "Ширина вмісту",
  "editor.digits_color.label": "Колір цифр",
  "editor.digits_font.label": "Шрифт цифр",
  "editor.digits_font_size.label": "Розмір шрифту цифр",
  "editor.do_not_stack_on_mobile.label": "Не складатися на мобільному",
  "editor.end_time.label": "Час завершення",
  "editor.fields.label": "Поля",
  "editor.font_family.label": "Сімейство шрифтів",
  "editor.font_size.label": "Розмір шрифту",
  "editor.form.custom": "Користувацький",
  "editor.form.method": "Метод",
  "editor.form_alignment.label": "Вирівнювання форми",
  "editor.form_width.label": "Ширина форми",
  "editor.full_width.label": "Повна ширина",
  "editor.heading_type.label": "Тип заголовка",
  "editor.height.label": "Висота",
  "editor.hide_on_desktop.label": "Приховати на робочому столі",
  "editor.hide_on_mobile.label": "Приховати на мобільному",
  "editor.hover_background.label": "Фон наведення",
  "editor.hover_color.label": "Колір наведення",
  "editor.hover_text.label": "Текст наведення",
  "editor.hover_underline.label": "Підкреслення наведення",
  "editor.icon_spacing.label": "Відстань між піктограмами",
  "editor.icon_type.label": "Тип піктограми",
  "editor.image.added_drawing": "Додано: малюнок",
  "editor.image.added_frame": "Додано: рамка",
  "editor.image.added_overlay_image": "Додано: зображення накладання",
  "editor.image.added_shape": "Додана: форма",
  "editor.image.added_sticker": "Додано: наклейка",
  "editor.image.added_text": "Додано: текст",
  "editor.image.applied_crop": "Застосовано: обтинання",
  "editor.image.applied_filter": "Застосовано: фільтр",
  "editor.image.applied_resize": "Застосовано: змінення розміру",
  "editor.image.applied_rounded_corners": "Застосовано: закруглені кути",
  "editor.image.applied_transform": "Застосовано: перетворення",
  "editor.image.auto": "Автоматично",
  "editor.image.auto_width": "Автоматична ширина",
  "editor.image.auto_width_switch_off": "Вимкнення автоматичної ширини для змінення розміру зображення вручну",
  "editor.image.brush_color": "Колір пензля",
  "editor.image.brush_size": "Розмір пензля",
  "editor.image.brush_type": "Тип пензля",
  "editor.image.canvas_background": "Фон полотна",
  "editor.image.changed_background": "Змінено: фон",
  "editor.image.changed_background_image": "Змінено: зображення фону",
  "editor.image.changed_style": "Змінено: стиль",
  "editor.image.drop_upload": "Перетягніть сюди нове зображення або натисніть, щоб вибрати файли для завантаження.",
  "editor.image.full_width_mobile": "Повна ширина на мобільному",
  "editor.image.image_options": "Параметри зображення",
  "editor.image.image_url": "URL-адреса зображення",
  "editor.image.initial": "Початковий",
  "editor.image.label": "Зображення",
  "editor.image.loaded_state": "Завантажено: стан",
  "editor.image.maintain_aspect_ratio": "Зберегти співвідношення сторін",
  "editor.image.main_image": "Основне зображення",
  "editor.image.objects_merged": "Об’єкти: об’єднано",
  "editor.image.offset_x": "Зсув X",
  "editor.image.offset_y": "Зсув Y",
  "editor.image.outline_width": "Ширина контуру",
  "editor.image.uploading": "Завантаження",
  "editor.image.upload_error": "Під час завантаження зображення сталася помилка. Переконайтеся, що файл зображення є припустимим і має розмір до {mbSize} МБ.",
  "editor.image.use_percentages": "Використовувати відсотки",
  "editor.image_link.label": "Посилання зображення",
  "editor.inherit_body_styles.label": "Успадкувати стилі основної частини",
  "editor.labels.web": "Веб",
  "editor.labels_color.label": "Колір міток",
  "editor.labels_font.label": "Шрифт міток",
  "editor.labels_font_size.label": "Розмір шрифту міток",
  "editor.layout.label": "Макет",
  "editor.left.label": "Ліворуч",
  "editor.line.label": "Рядок",
  "editor.line_height.label": "Висота рядка",
  "editor.link.body": "Основна частина",
  "editor.link.call_phone": "Зателефонувати за номером телефону",
  "editor.link.mailto": "Надіслати поштою",
  "editor.link.new_tab": "Нова вкладка",
  "editor.link.no_page_sections_found": "Не знайдено розділів сторінки",
  "editor.link.onclick_unsupported": "OnClick не підтримується",
  "editor.link.open_website": "Відкрити веб-сайт",
  "editor.link.page_section": "Перейти до розділу сторінки",
  "editor.link.phone": "Телефон",
  "editor.link.same_tab": "Однакова вкладка",
  "editor.link.send_email": "Надіслати повідомлення електронної пошти",
  "editor.link.send_sms": "Надіслати SMS",
  "editor.link.subject": "Тема",
  "editor.link.target": "Ціль",
  "editor.link.url": "URL-адреса",
  "editor.link_color.label": "Колір посилання",
  "editor.margin.label": "Поле",
  "editor.mobile.description": "Наразі здійснюється редагування для мобільних пристроїв. Перемкніться на робочий стіл для доступу до всіх параметрів стилю.",
  "editor.offline_mode_is_enabled": "Офлайн-режим увімкнений",
  "editor.padding.label": "Заповнення",
  "editor.placeholder.text": "Вміст відсутній. Перетягніть вміст справа.",
  "editor.placeholder.text.left": "Тут немає контенту. Перетягніть контент зліва.",
  "editor.play_icon_color.label": "Колір піктограми відтворення",
  "editor.play_icon_size.label": "Розмір піктограми відтворення",
  "editor.play_icon_type.label": "Тип піктограми відтворення",
  "editor.preheader_text.description": "Попередній заголовок - це короткий текст з підсумком, який йде за рядком теми листа, коли  дивитись електронного листа з папки \"Вхідні\".",
  "editor.preheader_text.label": "Текст попереднього заголовку",
  "editor.right.label": "Праворуч",
  "editor.rounded_border.label": "Закруглена межа",
  "editor.section_name.description": "Назва розділу використовується для посилання всередині сторінки. Він служить якорем для кнопок чи посилань.",
  "editor.section_name.label": "Назва розділу",
  "editor.separator.label": "Розділювач",
  "editor.social_links.label": "Посилання на соціальні мережі",
  "editor.space_between_fields.label": "Відстань між полями",
  "editor.submit_action.label": "Надіслати дію",
  "editor.text.label": "Текст",
  "editor.text_align.label": "Вирівнювання тексту",
  "editor.text_color.label": "Колір тексту",
  "editor.top.label": "Найпопулярніше",
  "editor.top_left.label": "Зверху зліва",
  "editor.top_right.label": "Зверху справа",
  "editor.underline.label": "Підкреслення",
  "editor.video.arrow_only": "Лише стрілка",
  "editor.video.video_camera": "Відеокамера",
  "editor.video_url.description": "Додайте URL-адресу YouTube або Vimeo, щоб автоматично створити зображення попереднього перегляду. Зображення буде пов’язано із зазначеною URL-адресою.",
  "editor.video_url.label": "URL-адреса відео",
  "editor.width.label": "Ширина",
  "editors_panel.title.content": "Вміст",
  "editors_panel.title.contents": "Вміст",
  "editors_panel.title.rows": "Рядок",
  "fields.birthday": "День народження",
  "fields.company": "Компанія",
  "fields.name": "Назва",
  "fields.phone_number": "Номер телефону",
  "fields.website": "Веб-сайт",
  "fields.zip_code": "Поштовий індекс",
  "inbox_preview.design_updated": "Дизайн був оновлений, відколи ви востаннє згенерували передогляд",
  "labels.align_text": "Вирівняти текст",
  "labels.blur": "Розмиття",
  "labels.category": "Категорія",
  "labels.color_picker": "Палітра кольорів",
  "labels.comments": "Коментарі",
  "labels.desktop_preview": "Попередній перегляд робочого столу",
  "labels.device_override": "Цей прилад перевищує величини",
  "labels.display_conditions": "Умови відображення",
  "labels.editor": "Редактор",
  "labels.font": "Шрифт",
  "labels.format_text": "Форматувати текст",
  "labels.google_fonts": "Шрифти Google",
  "labels.gradient": "Градієнт",
  "labels.hide": "Сховати",
  "labels.horizontal": "Горизонтально",
  "labels.language": "Мова",
  "labels.loading": "Завантаження",
  "labels.loading_images": "Завантаження зображень",
  "labels.load_more": "Завантажити більше",
  "labels.menu.links": "Посилання меню",
  "labels.merge_tags": "Об’єднати теги",
  "labels.mobile_preview": "Попередній перегляд для мобільних пристроїв",
  "labels.new": "Нове",
  "labels.no_images": "Немає зображень",
  "labels.no_results": "Немає результатів",
  "labels.objects": "Об’єкти",
  "labels.outline": "Контур",
  "labels.page": "Сторінка",
  "labels.radius": "Радіус",
  "labels.redo": "Повторити",
  "labels.safe_search": "Безпечний пошук",
  "labels.search": "Пошук",
  "labels.search_images": "Пошук мільйонів зображень",
  "labels.section": "Розділ",
  "labels.shadow": "Тінь",
  "labels.size": "Розмір",
  "labels.something_went_wrong": "Щось пішло не так",
  "labels.special_links": "Спеціальні посилання",
  "labels.stock_photos_by": "На платформі Unsplash, Pexels, Pixabay.",
  "labels.stock_photos_license": "Усі зображення ліцензовано за Creative Commons Zero.",
  "labels.stop": "Зупинити",
  "labels.tags": "Теги",
  "labels.texture": "Текстура",
  "labels.text_style": "Стиль тексту",
  "labels.timezone": "Часовий пояс",
  "labels.undo": "Скасувати",
  "labels.vertical": "Вертикально",
  "modals.category.invalid": "Неприпустима назва категорії",
  "modals.category.placeholder": "Назва категорії",
  "modals.delete.columns": "Ви втратите стільки стовпців: {columns}. Продовжити?",
  "modals.delete.confirmation": "Справді видалити цей елемент? Цю дію неможливо скасувати.",
  "modals.delete.title": "Видалити",
  "modals.display_conditions.title": "Вибрати умову відображення",
  "modals.preview.inbox_preview.button.generate_previews": "Згенерувати передогляди",
  "modals.preview.inbox_preview.label": "Передогляди вхідних",
  "modals.preview.inbox_preview.label.generating_again": "Згенерувати знову",
  "modals.preview.inbox_preview.label.generating_previews": "Генеруємо передогляди",
  "modals.preview.inbox_preview.text.generate_previews": "Перевірте, як ваш шаблон виглядатиме у вхідних на різних пристроях та у різних поштових службах.",
  "modals.preview.title": "Попередній перегляд",
  "modals.save_block.title": "Зберегти блок",
  "modals.tags.description": "Теги використовуються для пошуку. Кілька тегів можна розділити комою.",
  "modals.tags.placeholder": "тег1, тег2",
  "option_groups.action.title": "Дія",
  "option_groups.all.title": "Усе",
  "option_groups.blank.title": "Пусто",
  "option_groups.button.title": "Кнопка",
  "option_groups.button_options.title": "Опції кнопки",
  "option_groups.colors.title": "Кольори",
  "option_groups.columns.title": "Стовпці",
  "option_groups.column_number.title": "Стовпець {number}",
  "option_groups.column_properties.title": "Властивості стовпця",
  "option_groups.countdown.title": "Відлік",
  "option_groups.default.title": "Загальне",
  "option_groups.display_condition.title": "Умова відображення",
  "option_groups.email_settings.title": "Налаштування електронної пошти",
  "option_groups.fields.title": "Поля",
  "option_groups.form.title": "Форма",
  "option_groups.html.title": "HTML",
  "option_groups.icons.title": "Піктограми",
  "option_groups.image.title": "Зображення",
  "option_groups.labels.title": "Мітки",
  "option_groups.last_saved.title": "Останнє збереження",
  "option_groups.layout.title": "Макет",
  "option_groups.line.title": "Рядок",
  "option_groups.link.title": "Посилання",
  "option_groups.links.title": "Посилання",
  "option_groups.menu_items.title": "Елементи меню",
  "option_groups.mobile.title": "Мобільний",
  "option_groups.responsive_design.title": "Адаптивний дизайн",
  "option_groups.row_properties.title": "Властивості рядка",
  "option_groups.size.title": "Розмір",
  "option_groups.spacing.title": "Відстань",
  "option_groups.styles.title": "Стилі",
  "option_groups.text.title": "Текст",
  "shapes.circle": "Коло",
  "shapes.rectangle": "Прямокутник",
  "shapes.round": "Круг",
  "shapes.square": "Квадрат",
  "sizes.large": "Великий",
  "sizes.largest": "Найбільший",
  "sizes.medium": "Середній",
  "sizes.small": "Малий",
  "sizes.smallest": "Найменший",
  "tabs.audit.empty.description": "Перевірка — це те місце, де ви можете побачити всі проблеми в своєму дизайні та контенті",
  "tabs.audit.empty.subtitle": "Все добре!",
  "tabs.audit.empty.title": "Наразі проблем немає",
  "tabs.audit.missing_image_src": "Відсутня URL-адреса зображення",
  "tabs.audit.missing_title": "Відсутня назва перевірки",
  "tabs.audit.missing_tool_name": "Назву інструменту не знайдено",
  "tabs.audit.rules.button.empty_links.description": "Без посилання кнопки не працюватимуть, коли користувач натисне на них. Додайте посилання на такі кнопки.",
  "tabs.audit.rules.button.empty_links.title": "Посилання на кнопки порожні",
  "tabs.audit.rules.image.alt_text.description": "Без альернативного тексту люди, які використовують програми читання з екрану, не зможуть отримати доступ до інформації про зображення. Напишіть відповідний альтернативний текст для таких зображень.",
  "tabs.audit.rules.image.alt_text.title": "Відсутній альтернативний текст",
  "tabs.audit.rules.image.url.description": "Без URL-адреси зображення наступні зображення не відображатимуться. Завантажте зображення для таких зображень.",
  "tabs.audit.rules.image.url.title": "Відсутні зображення",
  "tabs.audit.rules.menu.empty_links.description": "Без посилання меню не працюватиме, коли користувач натискає на нього. Додайте відсутні посилання до такого меню.",
  "tabs.audit.rules.menu.empty_links.title": "Посилання меню порожні",
  "tabs.audit.take_me_to_fix": "Візьміть мене, щоб виправити",
  "tools.form.field_label": "Мітка поля",
  "tools.form.field_name": "Назва поля",
  "tools.form.field_type": "Тип поля",
  "tools.form.field_value": "Значення поля",
  "tools.form.new_field": "Нове поле",
  "tools.form.options_one_per_line": "Параметри (по одному на рядок)",
  "tools.form.placeholder_text": "Текст заповнювача",
  "tools.form.required_field": "Обов’язкове поле",
  "tools.form.show_label": "Показати мітку",
  "tools.form.update_field": "Оновити поле",
  "tools.social.click_icons_to_add": "Натисніть піктограми, які потрібно додати",
  "tools.tabs.audit": "Перевірка",
  "tools.tabs.blocks": "Блоки",
  "tools.tabs.body": "Основна частина",
  "tools.tabs.content": "Вміст",
  "tools.tabs.images": "Зображення",
  "tools.tabs.row": "Рядок",
  "tools.tabs.uploads": "Завантаження",
  "tools.text.personalize": "Персоналізувати",
  "tools.tooltip.drag_on_canvas": "Перетягніть на полотно",
  "tools.tooltip.got_it": "Зрозуміло"
}